{
  "date" : "2022_07_28_12_23_00",
  "random" : {
    "seed" : "8CV0N71E",
    "seedLong" : 5667864878554969,
    "publicRandom" : 151,
    "skillRandom" : 124,
    "itemRandom" : 339,
    "mapRandom" : 107,
    "monsterRandom" : 0,
    "eventRandom" : 2,
    "shopRandom" : 56
  },
  "restriction" : {
    "GRW" : 0,
    "STR" : 0,
    "INT" : 0,
    "HUG" : 0,
    "FAM" : 0,
    "FOG" : 0,
    "POV" : 0,
    "MSR" : 0,
    "FTG" : 0,
    "ANX" : 0
  },
  "itemAble" : 0,
  "selection" : 3,
  "maxEnergy" : 3,
  "gold" : 63,
  "bleak" : 0,
  "bleakMin" : 0,
  "bleakMax" : 100,
  "bleakAdd" : 9,
  "advisor" : {
    "cls" : "DOPA",
    "skill" : {
      "id" : "dopa",
      "usedOnly" : false,
      "upgradeCount" : 0
    }
  },
  "players" : [ {
    "id" : "burger",
    "item" : [ "Turtle", "Coffin" ],
    "deck" : [ {
      "id" : "HolySmite",
      "usedOnly" : false,
      "upgradeCount" : 0
    }, {
      "id" : "Bless",
      "usedOnly" : false,
      "upgradeCount" : 0
    }, {
      "id" : "SuperSave",
      "usedOnly" : false,
      "upgradeCount" : 0
    } ],
    "isDead" : false,
    "slot" : [ 0, 0, 0 ],
    "index" : 0,
    "maxHealth" : 37,
    "health" : 19
  }, {
    "id" : "viichan",
    "item" : [ "SilverItem2", "GoldItem12" ],
    "deck" : [ {
      "id" : "Onslaught",
      "usedOnly" : false,
      "upgradeCount" : 3
    }, {
      "id" : "Cross",
      "usedOnly" : false,
      "upgradeCount" : 0
    }, {
      "id" : "Stab",
      "usedOnly" : false,
      "upgradeCount" : 0
    } ],
    "isDead" : false,
    "slot" : [ 3, 0, 0 ],
    "index" : 1,
    "maxHealth" : 48,
    "health" : 35
  }, {
    "id" : "lilpa",
    "item" : [ "FlameBook", "NaviNecklace" ],
    "deck" : [ {
      "id" : "Strike",
      "usedOnly" : false,
      "upgradeCount" : 0
    }, {
      "id" : "Barrier",
      "usedOnly" : false,
      "upgradeCount" : 0
    }, {
      "id" : "ElectricFire",
      "usedOnly" : false,
      "upgradeCount" : 3
    } ],
    "isDead" : false,
    "slot" : [ 0, 0, 3 ],
    "index" : 2,
    "maxHealth" : 24,
    "health" : 24
  }, {
    "id" : "jururu",
    "item" : [ "GoldItem5", "ElasticRing" ],
    "deck" : [ {
      "id" : "Strike",
      "usedOnly" : false,
      "upgradeCount" : 0
    }, {
      "id" : "Barrier",
      "usedOnly" : false,
      "upgradeCount" : 0
    }, {
      "id" : "Scorn",
      "usedOnly" : false,
      "upgradeCount" : 2
    } ],
    "isDead" : false,
    "slot" : [ 0, 0, 2 ],
    "index" : 3,
    "maxHealth" : 42,
    "health" : 29
  } ],
  "currentFloor" : 2,
  "floors" : [ {
    "currentRoom" : {
      "id" : "Boss1",
      "battleDone" : true,
      "isDone" : true
    },
    "currentWay" : {
      "type" : "BOSS",
      "enemies" : {
        "id" : "Boss1",
        "battleDone" : true,
        "isDone" : true
      },
      "choices" : [ {
        "type" : "BOSS",
        "room" : {
          "id" : "Boss1",
          "battleDone" : true,
          "isDone" : true
        },
        "must" : true,
        "prob" : 1
      } ],
      "isDone" : true
    },
    "ways" : [ {
      "type" : "ENTRY",
      "enemies" : null,
      "choices" : [ {
        "type" : "GOOD",
        "room" : {
          "id" : "StartEvent",
          "battleDone" : false,
          "isDone" : true
        },
        "must" : true,
        "prob" : 1
      } ],
      "isDone" : true
    }, {
      "type" : "WEAK",
      "enemies" : {
        "id" : "Weak1",
        "battleDone" : true,
        "isDone" : true
      },
      "choices" : [ {
        "type" : "BATTLE",
        "room" : {
          "id" : "Weak1",
          "battleDone" : true,
          "isDone" : true
        },
        "must" : true,
        "prob" : 1
      }, {
        "type" : "REST",
        "room" : {
          "id" : "Rest",
          "battleDone" : false,
          "isDone" : false
        },
        "must" : true,
        "prob" : 1
      } ],
      "isDone" : true
    }, {
      "type" : "WEAK",
      "enemies" : {
        "id" : "Weak2",
        "battleDone" : false,
        "isDone" : false
      },
      "choices" : [ {
        "type" : "BATTLE",
        "room" : {
          "id" : "Weak2",
          "battleDone" : false,
          "isDone" : false
        },
        "must" : true,
        "prob" : 1
      }, {
        "type" : "LOOK",
        "room" : {
          "id" : "Mystery",
          "battleDone" : false,
          "isDone" : true
        },
        "must" : true,
        "prob" : 1
      }, {
        "type" : "REST",
        "room" : {
          "id" : "Rest",
          "battleDone" : false,
          "isDone" : false
        },
        "must" : true,
        "prob" : 1
      } ],
      "isDone" : true
    }, {
      "type" : "WEAK",
      "enemies" : {
        "id" : "Weak5",
        "battleDone" : true,
        "isDone" : true
      },
      "choices" : [ {
        "type" : "LOOK",
        "room" : {
          "id" : "Mystery",
          "battleDone" : false,
          "isDone" : false
        },
        "must" : true,
        "prob" : 1
      }, {
        "type" : "BATTLE",
        "room" : {
          "id" : "Weak5",
          "battleDone" : true,
          "isDone" : true
        },
        "must" : true,
        "prob" : 1
      }, {
        "type" : "REST",
        "room" : {
          "id" : "Rest",
          "battleDone" : false,
          "isDone" : false
        },
        "must" : true,
        "prob" : 1
      } ],
      "isDone" : true
    }, {
      "type" : "ELITE",
      "enemies" : {
        "id" : "Elite1",
        "battleDone" : true,
        "isDone" : true
      },
      "choices" : [ {
        "type" : "ELITE",
        "room" : {
          "id" : "Elite1",
          "battleDone" : true,
          "isDone" : true
        },
        "must" : true,
        "prob" : 1
      } ],
      "isDone" : true
    }, {
      "type" : "NORMAL",
      "enemies" : {
        "id" : "Normal4",
        "battleDone" : true,
        "isDone" : true
      },
      "choices" : [ {
        "type" : "REST",
        "room" : {
          "id" : "Rest",
          "battleDone" : false,
          "isDone" : false
        },
        "must" : true,
        "prob" : 1
      }, {
        "type" : "BATTLE",
        "room" : {
          "id" : "Normal4",
          "battleDone" : true,
          "isDone" : true
        },
        "must" : true,
        "prob" : 1
      } ],
      "isDone" : true
    }, {
      "type" : "SHOP",
      "enemies" : null,
      "choices" : [ {
        "type" : "SHOP",
        "room" : {
          "id" : "Shop",
          "battleDone" : false,
          "isDone" : true
        },
        "must" : true,
        "prob" : 1
      }, {
        "type" : "REST",
        "room" : {
          "id" : "Rest",
          "battleDone" : false,
          "isDone" : false
        },
        "must" : true,
        "prob" : 1
      } ],
      "isDone" : true
    }, {
      "type" : "NORMAL",
      "enemies" : {
        "id" : "Normal3",
        "battleDone" : false,
        "isDone" : false
      },
      "choices" : [ {
        "type" : "LOOK",
        "room" : {
          "id" : "Mystery",
          "battleDone" : false,
          "isDone" : true
        },
        "must" : true,
        "prob" : 1
      }, {
        "type" : "REST",
        "room" : {
          "id" : "Rest",
          "battleDone" : false,
          "isDone" : false
        },
        "must" : true,
        "prob" : 1
      }, {
        "type" : "BATTLE",
        "room" : {
          "id" : "Normal3",
          "battleDone" : false,
          "isDone" : false
        },
        "must" : true,
        "prob" : 1
      } ],
      "isDone" : true
    }, {
      "type" : "ELITE",
      "enemies" : {
        "id" : "Elite2",
        "battleDone" : true,
        "isDone" : true
      },
      "choices" : [ {
        "type" : "ELITE",
        "room" : {
          "id" : "Elite2",
          "battleDone" : true,
          "isDone" : true
        },
        "must" : true,
        "prob" : 1
      } ],
      "isDone" : true
    }, {
      "type" : "NORMAL",
      "enemies" : {
        "id" : "Normal2",
        "battleDone" : false,
        "isDone" : false
      },
      "choices" : [ {
        "type" : "LOOK",
        "room" : {
          "id" : "Shop",
          "battleDone" : false,
          "isDone" : true
        },
        "must" : true,
        "prob" : 1
      }, {
        "type" : "BATTLE",
        "room" : {
          "id" : "Normal2",
          "battleDone" : false,
          "isDone" : false
        },
        "must" : true,
        "prob" : 1
      } ],
      "isDone" : true
    }, {
      "type" : "NORMAL",
      "enemies" : {
        "id" : "Normal1",
        "battleDone" : true,
        "isDone" : true
      },
      "choices" : [ {
        "type" : "LOOK",
        "room" : {
          "id" : "Mystery",
          "battleDone" : false,
          "isDone" : false
        },
        "must" : true,
        "prob" : 1
      }, {
        "type" : "BATTLE",
        "room" : {
          "id" : "Normal1",
          "battleDone" : true,
          "isDone" : true
        },
        "must" : true,
        "prob" : 1
      } ],
      "isDone" : true
    }, {
      "type" : "REST",
      "enemies" : null,
      "choices" : [ {
        "type" : "REST",
        "room" : {
          "id" : "Rest",
          "battleDone" : false,
          "isDone" : true
        },
        "must" : true,
        "prob" : 1
      } ],
      "isDone" : true
    }, {
      "type" : "BOSS",
      "enemies" : {
        "id" : "Boss1",
        "battleDone" : true,
        "isDone" : true
      },
      "choices" : [ {
        "type" : "BOSS",
        "room" : {
          "id" : "Boss1",
          "battleDone" : true,
          "isDone" : true
        },
        "must" : true,
        "prob" : 1
      } ],
      "isDone" : true
    } ],
    "isDone" : true,
    "floorNum" : 1,
    "num" : 13
  }, {
    "currentRoom" : {
      "id" : "Weak5",
      "battleDone" : false,
      "isDone" : true
    },
    "currentWay" : {
      "type" : "WEAK",
      "enemies" : {
        "id" : "Weak5",
        "battleDone" : false,
        "isDone" : false
      },
      "choices" : [ {
        "type" : "REST",
        "room" : {
          "id" : "Rest",
          "battleDone" : false,
          "isDone" : false
        },
        "must" : true,
        "prob" : 1
      }, {
        "type" : "LOOK",
        "room" : {
          "id" : "Mystery",
          "battleDone" : false,
          "isDone" : false
        },
        "must" : true,
        "prob" : 1
      }, {
        "type" : "BATTLE",
        "room" : {
          "id" : "Weak5",
          "battleDone" : false,
          "isDone" : true
        },
        "must" : true,
        "prob" : 1
      } ],
      "isDone" : true
    },
    "ways" : [ {
      "type" : "ENTRY",
      "enemies" : null,
      "choices" : [ {
        "type" : "GOOD",
        "room" : {
          "id" : "SecondFloor",
          "battleDone" : false,
          "isDone" : true
        },
        "must" : true,
        "prob" : 1
      } ],
      "isDone" : true
    }, {
      "type" : "WEAK",
      "enemies" : {
        "id" : "Weak1",
        "battleDone" : false,
        "isDone" : false
      },
      "choices" : [ {
        "type" : "LOOK",
        "room" : {
          "id" : "Mystery",
          "battleDone" : false,
          "isDone" : false
        },
        "must" : true,
        "prob" : 1
      }, {
        "type" : "BATTLE",
        "room" : {
          "id" : "Weak1",
          "battleDone" : false,
          "isDone" : false
        },
        "must" : true,
        "prob" : 1
      } ],
      "isDone" : true
    }, {
      "type" : "WEAK",
      "enemies" : {
        "id" : "Weak2",
        "battleDone" : false,
        "isDone" : false
      },
      "choices" : [ {
        "type" : "BATTLE",
        "room" : {
          "id" : "Weak2",
          "battleDone" : false,
          "isDone" : true
        },
        "must" : true,
        "prob" : 1
      }, {
        "type" : "LOOK",
        "room" : {
          "id" : "Mystery",
          "battleDone" : false,
          "isDone" : false
        },
        "must" : true,
        "prob" : 1
      } ],
      "isDone" : true
    }, {
      "type" : "WEAK",
      "enemies" : {
        "id" : "Weak5",
        "battleDone" : false,
        "isDone" : false
      },
      "choices" : [ {
        "type" : "REST",
        "room" : {
          "id" : "Rest",
          "battleDone" : false,
          "isDone" : false
        },
        "must" : true,
        "prob" : 1
      }, {
        "type" : "LOOK",
        "room" : {
          "id" : "Mystery",
          "battleDone" : false,
          "isDone" : false
        },
        "must" : true,
        "prob" : 1
      }, {
        "type" : "BATTLE",
        "room" : {
          "id" : "Weak5",
          "battleDone" : false,
          "isDone" : true
        },
        "must" : true,
        "prob" : 1
      } ],
      "isDone" : true
    }, {
      "type" : "ELITE",
      "enemies" : {
        "id" : "Elite1",
        "battleDone" : false,
        "isDone" : false
      },
      "choices" : [ {
        "type" : "ELITE",
        "room" : {
          "id" : "Elite1",
          "battleDone" : false,
          "isDone" : false
        },
        "must" : true,
        "prob" : 1
      } ],
      "isDone" : false
    }, {
      "type" : "NORMAL",
      "enemies" : {
        "id" : "Normal4",
        "battleDone" : false,
        "isDone" : false
      },
      "choices" : [ {
        "type" : "LOOK",
        "room" : {
          "id" : "Mystery",
          "battleDone" : false,
          "isDone" : false
        },
        "must" : true,
        "prob" : 1
      }, {
        "type" : "BATTLE",
        "room" : {
          "id" : "Normal4",
          "battleDone" : false,
          "isDone" : false
        },
        "must" : true,
        "prob" : 1
      } ],
      "isDone" : false
    }, {
      "type" : "SHOP",
      "enemies" : null,
      "choices" : [ {
        "type" : "REST",
        "room" : {
          "id" : "Rest",
          "battleDone" : false,
          "isDone" : false
        },
        "must" : true,
        "prob" : 1
      }, {
        "type" : "SHOP",
        "room" : {
          "id" : "Shop",
          "battleDone" : false,
          "isDone" : false
        },
        "must" : true,
        "prob" : 1
      } ],
      "isDone" : false
    }, {
      "type" : "NORMAL",
      "enemies" : {
        "id" : "Normal3",
        "battleDone" : false,
        "isDone" : false
      },
      "choices" : [ {
        "type" : "LOOK",
        "room" : {
          "id" : "Mystery",
          "battleDone" : false,
          "isDone" : false
        },
        "must" : true,
        "prob" : 1
      }, {
        "type" : "BATTLE",
        "room" : {
          "id" : "Normal3",
          "battleDone" : false,
          "isDone" : false
        },
        "must" : true,
        "prob" : 1
      }, {
        "type" : "REST",
        "room" : {
          "id" : "Rest",
          "battleDone" : false,
          "isDone" : false
        },
        "must" : true,
        "prob" : 1
      } ],
      "isDone" : false
    }, {
      "type" : "ELITE",
      "enemies" : {
        "id" : "Elite2",
        "battleDone" : false,
        "isDone" : false
      },
      "choices" : [ {
        "type" : "ELITE",
        "room" : {
          "id" : "Elite2",
          "battleDone" : false,
          "isDone" : false
        },
        "must" : true,
        "prob" : 1
      } ],
      "isDone" : false
    }, {
      "type" : "NORMAL",
      "enemies" : {
        "id" : "Normal2",
        "battleDone" : false,
        "isDone" : false
      },
      "choices" : [ {
        "type" : "LOOK",
        "room" : {
          "id" : "Mystery",
          "battleDone" : false,
          "isDone" : false
        },
        "must" : true,
        "prob" : 1
      }, {
        "type" : "BATTLE",
        "room" : {
          "id" : "Normal2",
          "battleDone" : false,
          "isDone" : false
        },
        "must" : true,
        "prob" : 1
      }, {
        "type" : "REST",
        "room" : {
          "id" : "Rest",
          "battleDone" : false,
          "isDone" : false
        },
        "must" : true,
        "prob" : 1
      } ],
      "isDone" : false
    }, {
      "type" : "NORMAL",
      "enemies" : {
        "id" : "Normal1",
        "battleDone" : false,
        "isDone" : false
      },
      "choices" : [ {
        "type" : "BATTLE",
        "room" : {
          "id" : "Normal1",
          "battleDone" : false,
          "isDone" : false
        },
        "must" : true,
        "prob" : 1
      }, {
        "type" : "LOOK",
        "room" : {
          "id" : "Mystery",
          "battleDone" : false,
          "isDone" : false
        },
        "must" : true,
        "prob" : 1
      } ],
      "isDone" : false
    }, {
      "type" : "REST",
      "enemies" : null,
      "choices" : [ {
        "type" : "REST",
        "room" : {
          "id" : "Rest",
          "battleDone" : false,
          "isDone" : false
        },
        "must" : true,
        "prob" : 1
      } ],
      "isDone" : false
    }, {
      "type" : "BOSS",
      "enemies" : {
        "id" : "Boss2",
        "battleDone" : false,
        "isDone" : false
      },
      "choices" : [ {
        "type" : "BOSS",
        "room" : {
          "id" : "Boss2",
          "battleDone" : false,
          "isDone" : false
        },
        "must" : true,
        "prob" : 1
      } ],
      "isDone" : false
    } ],
    "isDone" : false,
    "floorNum" : 2,
    "num" : 4
  }, {
    "currentRoom" : {
      "id" : "Placeholder",
      "battleDone" : true,
      "isDone" : true
    },
    "currentWay" : null,
    "ways" : [ {
      "type" : "ENTRY",
      "enemies" : null,
      "choices" : [ {
        "type" : "GOOD",
        "room" : {
          "id" : "StartEvent",
          "battleDone" : false,
          "isDone" : false
        },
        "must" : true,
        "prob" : 1
      } ],
      "isDone" : false
    }, {
      "type" : "WEAK",
      "enemies" : {
        "id" : "Weak1",
        "battleDone" : false,
        "isDone" : false
      },
      "choices" : [ {
        "type" : "BATTLE",
        "room" : {
          "id" : "Weak1",
          "battleDone" : false,
          "isDone" : false
        },
        "must" : true,
        "prob" : 1
      }, {
        "type" : "LOOK",
        "room" : {
          "id" : "Mystery",
          "battleDone" : false,
          "isDone" : false
        },
        "must" : true,
        "prob" : 1
      } ],
      "isDone" : false
    }, {
      "type" : "WEAK",
      "enemies" : {
        "id" : "Weak2",
        "battleDone" : false,
        "isDone" : false
      },
      "choices" : [ {
        "type" : "REST",
        "room" : {
          "id" : "Rest",
          "battleDone" : false,
          "isDone" : false
        },
        "must" : true,
        "prob" : 1
      }, {
        "type" : "BATTLE",
        "room" : {
          "id" : "Weak2",
          "battleDone" : false,
          "isDone" : false
        },
        "must" : true,
        "prob" : 1
      }, {
        "type" : "LOOK",
        "room" : {
          "id" : "Mystery",
          "battleDone" : false,
          "isDone" : false
        },
        "must" : true,
        "prob" : 1
      } ],
      "isDone" : false
    }, {
      "type" : "WEAK",
      "enemies" : {
        "id" : "Weak5",
        "battleDone" : false,
        "isDone" : false
      },
      "choices" : [ {
        "type" : "LOOK",
        "room" : {
          "id" : "Mystery",
          "battleDone" : false,
          "isDone" : false
        },
        "must" : true,
        "prob" : 1
      }, {
        "type" : "BATTLE",
        "room" : {
          "id" : "Weak5",
          "battleDone" : false,
          "isDone" : false
        },
        "must" : true,
        "prob" : 1
      } ],
      "isDone" : false
    }, {
      "type" : "ELITE",
      "enemies" : {
        "id" : "Elite1",
        "battleDone" : false,
        "isDone" : false
      },
      "choices" : [ {
        "type" : "ELITE",
        "room" : {
          "id" : "Elite1",
          "battleDone" : false,
          "isDone" : false
        },
        "must" : true,
        "prob" : 1
      } ],
      "isDone" : false
    }, {
      "type" : "NORMAL",
      "enemies" : {
        "id" : "Normal4",
        "battleDone" : false,
        "isDone" : false
      },
      "choices" : [ {
        "type" : "REST",
        "room" : {
          "id" : "Rest",
          "battleDone" : false,
          "isDone" : false
        },
        "must" : true,
        "prob" : 1
      }, {
        "type" : "LOOK",
        "room" : {
          "id" : "Mystery",
          "battleDone" : false,
          "isDone" : false
        },
        "must" : true,
        "prob" : 1
      }, {
        "type" : "BATTLE",
        "room" : {
          "id" : "Normal4",
          "battleDone" : false,
          "isDone" : false
        },
        "must" : true,
        "prob" : 1
      } ],
      "isDone" : false
    }, {
      "type" : "SHOP",
      "enemies" : null,
      "choices" : [ {
        "type" : "REST",
        "room" : {
          "id" : "Rest",
          "battleDone" : false,
          "isDone" : false
        },
        "must" : true,
        "prob" : 1
      }, {
        "type" : "SHOP",
        "room" : {
          "id" : "Shop",
          "battleDone" : false,
          "isDone" : false
        },
        "must" : true,
        "prob" : 1
      } ],
      "isDone" : false
    }, {
      "type" : "NORMAL",
      "enemies" : {
        "id" : "Normal3",
        "battleDone" : false,
        "isDone" : false
      },
      "choices" : [ {
        "type" : "LOOK",
        "room" : {
          "id" : "Mystery",
          "battleDone" : false,
          "isDone" : false
        },
        "must" : true,
        "prob" : 1
      }, {
        "type" : "BATTLE",
        "room" : {
          "id" : "Normal3",
          "battleDone" : false,
          "isDone" : false
        },
        "must" : true,
        "prob" : 1
      } ],
      "isDone" : false
    }, {
      "type" : "ELITE",
      "enemies" : {
        "id" : "Elite2",
        "battleDone" : false,
        "isDone" : false
      },
      "choices" : [ {
        "type" : "ELITE",
        "room" : {
          "id" : "Elite2",
          "battleDone" : false,
          "isDone" : false
        },
        "must" : true,
        "prob" : 1
      } ],
      "isDone" : false
    }, {
      "type" : "NORMAL",
      "enemies" : {
        "id" : "Normal2",
        "battleDone" : false,
        "isDone" : false
      },
      "choices" : [ {
        "type" : "BATTLE",
        "room" : {
          "id" : "Normal2",
          "battleDone" : false,
          "isDone" : false
        },
        "must" : true,
        "prob" : 1
      }, {
        "type" : "LOOK",
        "room" : {
          "id" : "Mystery",
          "battleDone" : false,
          "isDone" : false
        },
        "must" : true,
        "prob" : 1
      }, {
        "type" : "REST",
        "room" : {
          "id" : "Rest",
          "battleDone" : false,
          "isDone" : false
        },
        "must" : true,
        "prob" : 1
      } ],
      "isDone" : false
    }, {
      "type" : "NORMAL",
      "enemies" : {
        "id" : "Normal1",
        "battleDone" : false,
        "isDone" : false
      },
      "choices" : [ {
        "type" : "LOOK",
        "room" : {
          "id" : "Mystery",
          "battleDone" : false,
          "isDone" : false
        },
        "must" : true,
        "prob" : 1
      }, {
        "type" : "REST",
        "room" : {
          "id" : "Rest",
          "battleDone" : false,
          "isDone" : false
        },
        "must" : true,
        "prob" : 1
      }, {
        "type" : "BATTLE",
        "room" : {
          "id" : "Normal1",
          "battleDone" : false,
          "isDone" : false
        },
        "must" : true,
        "prob" : 1
      } ],
      "isDone" : false
    }, {
      "type" : "REST",
      "enemies" : null,
      "choices" : [ {
        "type" : "REST",
        "room" : {
          "id" : "Rest",
          "battleDone" : false,
          "isDone" : false
        },
        "must" : true,
        "prob" : 1
      } ],
      "isDone" : false
    }, {
      "type" : "BOSS",
      "enemies" : {
        "id" : "Boss2",
        "battleDone" : false,
        "isDone" : false
      },
      "choices" : [ {
        "type" : "BOSS",
        "room" : {
          "id" : "Boss2",
          "battleDone" : false,
          "isDone" : false
        },
        "must" : true,
        "prob" : 1
      } ],
      "isDone" : false
    } ],
    "isDone" : false,
    "floorNum" : 3,
    "num" : 0
  }, {
    "currentRoom" : {
      "id" : "Placeholder",
      "battleDone" : true,
      "isDone" : true
    },
    "currentWay" : null,
    "ways" : [ {
      "type" : "ENTRY",
      "enemies" : null,
      "choices" : [ {
        "type" : "GOOD",
        "room" : {
          "id" : "StartEvent",
          "battleDone" : false,
          "isDone" : false
        },
        "must" : true,
        "prob" : 1
      } ],
      "isDone" : false
    }, {
      "type" : "WEAK",
      "enemies" : {
        "id" : "Weak1",
        "battleDone" : false,
        "isDone" : false
      },
      "choices" : [ {
        "type" : "LOOK",
        "room" : {
          "id" : "Mystery",
          "battleDone" : false,
          "isDone" : false
        },
        "must" : true,
        "prob" : 1
      }, {
        "type" : "BATTLE",
        "room" : {
          "id" : "Weak1",
          "battleDone" : false,
          "isDone" : false
        },
        "must" : true,
        "prob" : 1
      } ],
      "isDone" : false
    }, {
      "type" : "WEAK",
      "enemies" : {
        "id" : "Weak2",
        "battleDone" : false,
        "isDone" : false
      },
      "choices" : [ {
        "type" : "BATTLE",
        "room" : {
          "id" : "Weak2",
          "battleDone" : false,
          "isDone" : false
        },
        "must" : true,
        "prob" : 1
      }, {
        "type" : "LOOK",
        "room" : {
          "id" : "Mystery",
          "battleDone" : false,
          "isDone" : false
        },
        "must" : true,
        "prob" : 1
      } ],
      "isDone" : false
    }, {
      "type" : "WEAK",
      "enemies" : {
        "id" : "Weak5",
        "battleDone" : false,
        "isDone" : false
      },
      "choices" : [ {
        "type" : "REST",
        "room" : {
          "id" : "Rest",
          "battleDone" : false,
          "isDone" : false
        },
        "must" : true,
        "prob" : 1
      }, {
        "type" : "BATTLE",
        "room" : {
          "id" : "Weak5",
          "battleDone" : false,
          "isDone" : false
        },
        "must" : true,
        "prob" : 1
      }, {
        "type" : "LOOK",
        "room" : {
          "id" : "Mystery",
          "battleDone" : false,
          "isDone" : false
        },
        "must" : true,
        "prob" : 1
      } ],
      "isDone" : false
    }, {
      "type" : "ELITE",
      "enemies" : {
        "id" : "Elite1",
        "battleDone" : false,
        "isDone" : false
      },
      "choices" : [ {
        "type" : "ELITE",
        "room" : {
          "id" : "Elite1",
          "battleDone" : false,
          "isDone" : false
        },
        "must" : true,
        "prob" : 1
      } ],
      "isDone" : false
    }, {
      "type" : "NORMAL",
      "enemies" : {
        "id" : "Normal4",
        "battleDone" : false,
        "isDone" : false
      },
      "choices" : [ {
        "type" : "REST",
        "room" : {
          "id" : "Rest",
          "battleDone" : false,
          "isDone" : false
        },
        "must" : true,
        "prob" : 1
      }, {
        "type" : "LOOK",
        "room" : {
          "id" : "Mystery",
          "battleDone" : false,
          "isDone" : false
        },
        "must" : true,
        "prob" : 1
      }, {
        "type" : "BATTLE",
        "room" : {
          "id" : "Normal4",
          "battleDone" : false,
          "isDone" : false
        },
        "must" : true,
        "prob" : 1
      } ],
      "isDone" : false
    }, {
      "type" : "SHOP",
      "enemies" : null,
      "choices" : [ {
        "type" : "REST",
        "room" : {
          "id" : "Rest",
          "battleDone" : false,
          "isDone" : false
        },
        "must" : true,
        "prob" : 1
      }, {
        "type" : "SHOP",
        "room" : {
          "id" : "Shop",
          "battleDone" : false,
          "isDone" : false
        },
        "must" : true,
        "prob" : 1
      } ],
      "isDone" : false
    }, {
      "type" : "NORMAL",
      "enemies" : {
        "id" : "Normal3",
        "battleDone" : false,
        "isDone" : false
      },
      "choices" : [ {
        "type" : "LOOK",
        "room" : {
          "id" : "Mystery",
          "battleDone" : false,
          "isDone" : false
        },
        "must" : true,
        "prob" : 1
      }, {
        "type" : "BATTLE",
        "room" : {
          "id" : "Normal3",
          "battleDone" : false,
          "isDone" : false
        },
        "must" : true,
        "prob" : 1
      } ],
      "isDone" : false
    }, {
      "type" : "ELITE",
      "enemies" : {
        "id" : "Elite2",
        "battleDone" : false,
        "isDone" : false
      },
      "choices" : [ {
        "type" : "ELITE",
        "room" : {
          "id" : "Elite2",
          "battleDone" : false,
          "isDone" : false
        },
        "must" : true,
        "prob" : 1
      } ],
      "isDone" : false
    }, {
      "type" : "NORMAL",
      "enemies" : {
        "id" : "Normal2",
        "battleDone" : false,
        "isDone" : false
      },
      "choices" : [ {
        "type" : "BATTLE",
        "room" : {
          "id" : "Normal2",
          "battleDone" : false,
          "isDone" : false
        },
        "must" : true,
        "prob" : 1
      }, {
        "type" : "REST",
        "room" : {
          "id" : "Rest",
          "battleDone" : false,
          "isDone" : false
        },
        "must" : true,
        "prob" : 1
      } ],
      "isDone" : false
    }, {
      "type" : "NORMAL",
      "enemies" : {
        "id" : "Normal1",
        "battleDone" : false,
        "isDone" : false
      },
      "choices" : [ {
        "type" : "LOOK",
        "room" : {
          "id" : "Mystery",
          "battleDone" : false,
          "isDone" : false
        },
        "must" : true,
        "prob" : 1
      }, {
        "type" : "BATTLE",
        "room" : {
          "id" : "Normal1",
          "battleDone" : false,
          "isDone" : false
        },
        "must" : true,
        "prob" : 1
      } ],
      "isDone" : false
    }, {
      "type" : "REST",
      "enemies" : null,
      "choices" : [ {
        "type" : "REST",
        "room" : {
          "id" : "Rest",
          "battleDone" : false,
          "isDone" : false
        },
        "must" : true,
        "prob" : 1
      } ],
      "isDone" : false
    }, {
      "type" : "BOSS",
      "enemies" : {
        "id" : "Boss2",
        "battleDone" : false,
        "isDone" : false
      },
      "choices" : [ {
        "type" : "BOSS",
        "room" : {
          "id" : "Boss2",
          "battleDone" : false,
          "isDone" : false
        },
        "must" : true,
        "prob" : 1
      } ],
      "isDone" : false
    } ],
    "isDone" : false,
    "floorNum" : 4,
    "num" : 0
  } ],
  "eventCount" : 0,
  "neutCount" : 1,
  "weakCount" : 0,
  "normalCount" : 0,
  "eliteCount" : 0,
  "bossCount" : 0
}